html2dict.py
html2dict/__init__.py
html2dict/base_extractor.py
html2dict/extractors.py
html2dict/resources.py
html2dict-0.2.dist-info/METADATA
html2dict-0.2.dist-info/RECORD
html2dict-0.2.dist-info/WHEEL
html2dict-0.2.dist-info/top_level.txt
