Metadata-Version: 2.1
Name: html2dict
Version: 0.2
Summary: Simple html tables extractor.
Home-page: https://github.com/B-Souty/html2dict
Author: B-Souty
Author-email: benjamin.souty@gmail.com
License: MIT
Platform: UNKNOWN
Classifier: License :: OSI Approved :: MIT License
Classifier: Programming Language :: Python
Classifier: Programming Language :: Python :: 3
Classifier: Programming Language :: Python :: 3.6
Requires-Python: >=3.6.0
Requires-Dist: lxml
Requires-Dist: requests
